LICENSE
MANIFEST.in
README.rst
setup.cfg
setup.py
docs/Makefile
docs/changelog.rst
docs/commandline.rst
docs/conf.py
docs/index.rst
docs/installation.rst
docs/make.bat
docs/python.rst
docs/specifics.rst
imagemounter/__init__.py
imagemounter/_util.py
imagemounter/disk.py
imagemounter/exceptions.py
imagemounter/parser.py
imagemounter/unmounter.py
imagemounter/volume.py
imagemounter/volume_system.py
imagemounter.egg-info/PKG-INFO
imagemounter.egg-info/SOURCES.txt
imagemounter.egg-info/dependency_links.txt
imagemounter.egg-info/entry_points.txt
imagemounter.egg-info/requires.txt
imagemounter.egg-info/top_level.txt
imagemounter/cli/__init__.py
imagemounter/cli/imount.py
imagemounter/cli/shell.py
test/__init__.py
test/basetest.py
test/cramfs_test.py
test/ext3_test.py
test/fat12_test.py
test/iso_test.py
test/minix_test.py
test/zip_test.py
test/images/test.cramfs
test/images/test.ext3
test/images/test.fat12
test/images/test.iso
test/images/test.mbr
test/images/test.minix
test/images/test.ntfs
test/images/test.sqsh
test/images/test.zip