Metadata-Version: 1.1
Name: imagemounter
Version: 3.0.1
Summary: Command line utility and Python package to ease the (un)mounting of forensic disk images.
Home-page: https://github.com/ralphje/imagemounter
Author: Peter Wagenaar, Ralph Broenink
Author-email: ralph@ralphbroenink.net
License: MIT
Download-URL: https://github.com/ralphje/imagemounter/tarball/v3.0.1
Keywords: encase,aff,dd,disk image,ewfmount,affuse,xmount,imount
Platform: UNKNOWN
Classifier: Development Status :: 5 - Production/Stable
Classifier: Environment :: Console
Classifier: Intended Audience :: Developers
Classifier: Intended Audience :: Legal Industry
Classifier: Intended Audience :: System Administrators
Classifier: License :: OSI Approved :: MIT License
Classifier: Operating System :: POSIX :: Linux
Classifier: Programming Language :: Python :: 2.7
Classifier: Programming Language :: Python :: 3.3
Classifier: Programming Language :: Python :: 3.4
Classifier: Programming Language :: Python :: 3.5
Classifier: Programming Language :: Python :: 3.6
Classifier: Topic :: Scientific/Engineering :: Information Analysis
Classifier: Topic :: System :: Filesystems
Classifier: Topic :: Terminals
Classifier: Topic :: Utilities
